{
  "type": "FeatureCollection",
  "features": [
    {
      "type": "Feature",
      "id": "70",
      "geometry": {
        "type": "Polygon",
        "coordinates": [
          [
            [
              -72.9790,
              42.5416
            ],
            [
              -72.9686,
              42.5400
            ],
            [
              -72.9794,
              42.4978
            ],
            [
              -72.9865,
              42.4667
            ],
            [
              -72.9882,
              42.4668
            ],
            [
              -73.0032,
              42.4096
            ],
            [
              -73.0117,
              42.3798
            ],
            [
              -73.0659,
              42.3890
            ],
            [
              -73.0686,
              42.3807
            ],
            [
              -73.0914,
              42.3848
            ],
            [
              -73.0844,
              42.4099
            ],
            [
              -73.0816,
              42.4094
            ],
            [
              -73.0788,
              42.4206
            ],
            [
              -73.0795,
              42.4225
            ],
            [
              -73.0807,
              42.4227
            ],
            [
              -73.0835,
              42.4240
            ],
            [
              -73.0829,
              42.4243
            ],
            [
              -73.0829,
              42.4251
            ],
            [
              -73.0817,
              42.4253
            ],
            [
              -73.0810,
              42.4249
            ],
            [
              -73.0817,
              42.4247
            ],
            [
              -73.0816,
              42.4244
            ],
            [
              -73.0797,
              42.4240
            ],
            [
              -73.0777,
              42.4253
            ],
            [
              -73.0774,
              42.4262
            ],
            [
              -73.0764,
              42.4262
            ],
            [
              -73.0759,
              42.4265
            ],
            [
              -73.0761,
              42.4274
            ],
            [
              -73.0771,
              42.4279
            ],
            [
              -73.0766,
              42.4286
            ],
            [
              -73.0775,
              42.4294
            ],
            [
              -73.0769,
              42.4299
            ],
            [
              -73.0791,
              42.4316
            ],
            [
              -73.0791,
              42.4322
            ],
            [
              -73.0805,
              42.4326
            ],
            [
              -73.0761,
              42.4460
            ],
            [
              -73.0774,
              42.4460
            ],
            [
              -73.0771,
              42.4472
            ],
            [
              -73.0795,
              42.4473
            ],
            [
              -73.0732,
              42.4684
            ],
            [
              -73.0714,
              42.4680
            ],
            [
              -73.0680,
              42.4801
            ],
            [
              -73.1151,
              42.4878
            ],
            [
              -73.1137,
              42.4924
            ],
            [
              -73.1203,
              42.4935
            ],
            [
              -73.1038,
              42.5508
            ],
            [
              -73.0886,
              42.5484
            ],
            [
              -73.0854,
              42.5595
            ],
            [
              -72.9790,
              42.5416
            ]
          ]
        ]
      },
      "properties": {
        "bound": {
          "minx": -73.11731315762194,
          "miny": 42.37833064151131,
          "maxx": -72.96904217755056,
          "maxy": 42.56104165364456
        },
        "Geoid10": 25003931648.000000
      }
    },
    {
      "type": "Feature",
      "id": "73",
      "geometry": {
        "type": "Polygon",
        "coordinates": [
          [
            [
              -73.0229,
              42.7411
            ],
            [
              -73.0237,
              42.7027
            ],
            [
              -72.9979,
              42.7013
            ],
            [
              -72.9497,
              42.7051
            ],
            [
              -72.9488,
              42.7041
            ],
            [
              -72.9498,
              42.7017
            ],
            [
              -72.9538,
              42.6986
            ],
            [
              -72.9538,
              42.6982
            ],
            [
              -72.9516,
              42.6955
            ],
            [
              -72.9515,
              42.6941
            ],
            [
              -72.9520,
              42.6927
            ],
            [
              -72.9546,
              42.6901
            ],
            [
              -72.9584,
              42.6900
            ],
            [
              -72.9609,
              42.6885
            ],
            [
              -72.9632,
              42.6877
            ],
            [
              -72.9652,
              42.6877
            ],
            [
              -72.9713,
              42.6890
            ],
            [
              -72.9747,
              42.6887
            ],
            [
              -72.9760,
              42.6864
            ],
            [
              -72.9776,
              42.6857
            ],
            [
              -72.9770,
              42.6831
            ],
            [
              -72.9755,
              42.6805
            ],
            [
              -72.9756,
              42.6797
            ],
            [
              -72.9762,
              42.6791
            ],
            [
              -72.9849,
              42.6792
            ],
            [
              -72.9894,
              42.6785
            ],
            [
              -72.9898,
              42.6782
            ],
            [
              -72.9886,
              42.6758
            ],
            [
              -72.9886,
              42.6744
            ],
            [
              -72.9901,
              42.6741
            ],
            [
              -72.9949,
              42.6744
            ],
            [
              -72.9957,
              42.6738
            ],
            [
              -72.9944,
              42.6721
            ],
            [
              -72.9886,
              42.6673
            ],
            [
              -72.9849,
              42.6658
            ],
            [
              -72.9811,
              42.6647
            ],
            [
              -72.9769,
              42.6615
            ],
            [
              -72.9757,
              42.6609
            ],
            [
              -72.9746,
              42.6611
            ],
            [
              -72.9724,
              42.6630
            ],
            [
              -72.9702,
              42.6639
            ],
            [
              -72.9683,
              42.6642
            ],
            [
              -72.9662,
              42.6640
            ],
            [
              -72.9640,
              42.6642
            ],
            [
              -72.9633,
              42.6648
            ],
            [
              -72.9623,
              42.6668
            ],
            [
              -72.9609,
              42.6673
            ],
            [
              -72.9570,
              42.6668
            ],
            [
              -72.9551,
              42.6659
            ],
            [
              -72.9546,
              42.6650
            ],
            [
              -72.9545,
              42.6623
            ],
            [
              -72.9557,
              42.6584
            ],
            [
              -72.9556,
              42.6546
            ],
            [
              -72.9541,
              42.6514
            ],
            [
              -72.9528,
              42.6509
            ],
            [
              -72.9511,
              42.6415
            ],
            [
              -72.9754,
              42.5559
            ],
            [
              -72.9791,
              42.5416
            ],
            [
              -73.0956,
              42.5612
            ],
            [
              -73.0805,
              42.5736
            ],
            [
              -73.0843,
              42.5947
            ],
            [
              -73.0675,
              42.5940
            ],
            [
              -73.0595,
              42.7084
            ],
            [
              -73.0485,
              42.7415
            ],
            [
              -73.0229,
              42.7411
            ]
          ]
        ]
      },
      "properties": {
        "bound": {
          "minx": -73.09501754860416,
          "miny": 42.540074697564506,
          "maxx": -72.94964855701139,
          "maxy": 42.7427729188945
        },
        "Geoid10": 25003931648.000000
      }
    },
    {
      "type": "Feature",
      "id": "489",
      "geometry": {
        "type": "Polygon",
        "coordinates": [
          [
            [
              -72.6118,
              42.6061
            ],
            [
              -72.6113,
              42.6041
            ],
            [
              -72.6110,
              42.6004
            ],
            [
              -72.6114,
              42.5950
            ],
            [
              -72.6111,
              42.5915
            ],
            [
              -72.6115,
              42.5860
            ],
            [
              -72.6127,
              42.5855
            ],
            [
              -72.6108,
              42.5830
            ],
            [
              -72.6082,
              42.5823
            ],
            [
              -72.6065,
              42.5825
            ],
            [
              -72.6032,
              42.5850
            ],
            [
              -72.6017,
              42.5852
            ],
            [
              -72.6008,
              42.5850
            ],
            [
              -72.5990,
              42.5825
            ],
            [
              -72.5956,
              42.5751
            ],
            [
              -72.5933,
              42.5722
            ],
            [
              -72.5922,
              42.5718
            ],
            [
              -72.5915,
              42.5698
            ],
            [
              -72.5926,
              42.5690
            ],
            [
              -72.5939,
              42.5667
            ],
            [
              -72.5947,
              42.5663
            ],
            [
              -72.5965,
              42.5665
            ],
            [
              -72.5990,
              42.5676
            ],
            [
              -72.6010,
              42.5693
            ],
            [
              -72.6018,
              42.5711
            ],
            [
              -72.6033,
              42.5719
            ],
            [
              -72.6057,
              42.5717
            ],
            [
              -72.6088,
              42.5700
            ],
            [
              -72.6137,
              42.5698
            ],
            [
              -72.6159,
              42.5702
            ],
            [
              -72.6178,
              42.5698
            ],
            [
              -72.6202,
              42.5703
            ],
            [
              -72.6204,
              42.5765
            ],
            [
              -72.6217,
              42.5821
            ],
            [
              -72.6216,
              42.5840
            ],
            [
              -72.6153,
              42.6018
            ],
            [
              -72.6120,
              42.6067
            ],
            [
              -72.6118,
              42.6061
            ]
          ]
        ]
      },
      "properties": {
        "bound": {
          "minx": -72.62144303944609,
          "miny": 42.5660126329372,
          "maxx": -72.59215748374903,
          "maxy": 42.60684025396544
        },
        "Geoid10": 25011042304.000000
      }
    },
    {
      "type": "Feature",
      "id": "520",
      "geometry": {
        "type": "Polygon",
        "coordinates": [
          [
            [
              -72.6368,
              42.5780
            ],
            [
              -72.6389,
              42.5700
            ],
            [
              -72.6520,
              42.5686
            ],
            [
              -72.6553,
              42.5552
            ],
            [
              -72.6757,
              42.5530
            ],
            [
              -72.6789,
              42.5560
            ],
            [
              -72.6796,
              42.5592
            ],
            [
              -72.6794,
              42.5617
            ],
            [
              -72.6802,
              42.5627
            ],
            [
              -72.6817,
              42.5629
            ],
            [
              -72.6853,
              42.5625
            ],
            [
              -72.6909,
              42.5641
            ],
            [
              -72.6927,
              42.5644
            ],
            [
              -72.6948,
              42.5643
            ],
            [
              -72.7003,
              42.5636
            ],
            [
              -72.7038,
              42.5647
            ],
            [
              -72.7054,
              42.5662
            ],
            [
              -72.7067,
              42.5685
            ],
            [
              -72.7072,
              42.5716
            ],
            [
              -72.7071,
              42.5728
            ],
            [
              -72.7065,
              42.5729
            ],
            [
              -72.7066,
              42.5733
            ],
            [
              -72.7073,
              42.5733
            ],
            [
              -72.7070,
              42.5754
            ],
            [
              -72.7068,
              42.5750
            ],
            [
              -72.7064,
              42.5757
            ],
            [
              -72.7064,
              42.5767
            ],
            [
              -72.7086,
              42.5780
            ],
            [
              -72.7112,
              42.5785
            ],
            [
              -72.7152,
              42.5803
            ],
            [
              -72.7172,
              42.5822
            ],
            [
              -72.7182,
              42.5848
            ],
            [
              -72.7193,
              42.5855
            ],
            [
              -72.7422,
              42.5831
            ],
            [
              -72.7454,
              42.5643
            ],
            [
              -72.7754,
              42.5680
            ],
            [
              -72.8485,
              42.5591
            ],
            [
              -72.8317,
              42.6166
            ],
            [
              -72.8225,
              42.6188
            ],
            [
              -72.8207,
              42.6186
            ],
            [
              -72.8170,
              42.6171
            ],
            [
              -72.8150,
              42.6167
            ],
            [
              -72.8085,
              42.6170
            ],
            [
              -72.8031,
              42.6166
            ],
            [
              -72.7979,
              42.6176
            ],
            [
              -72.7889,
              42.6202
            ],
            [
              -72.7835,
              42.6213
            ],
            [
              -72.7784,
              42.6211
            ],
            [
              -72.7728,
              42.6201
            ],
            [
              -72.7643,
              42.6194
            ],
            [
              -72.7592,
              42.6199
            ],
            [
              -72.7541,
              42.6210
            ],
            [
              -72.7522,
              42.6201
            ],
            [
              -72.7501,
              42.6182
            ],
            [
              -72.7484,
              42.6180
            ],
            [
              -72.7453,
              42.6197
            ],
            [
              -72.7455,
              42.6213
            ],
            [
              -72.7469,
              42.6227
            ],
            [
              -72.7467,
              42.6242
            ],
            [
              -72.7449,
              42.6261
            ],
            [
              -72.7434,
              42.6271
            ],
            [
              -72.7413,
              42.6275
            ],
            [
              -72.7369,
              42.6270
            ],
            [
              -72.7370,
              42.6289
            ],
            [
              -72.7363,
              42.6313
            ],
            [
              -72.7361,
              42.6321
            ],
            [
              -72.7350,
              42.6332
            ],
            [
              -72.6329,
              42.6454
            ],
            [
              -72.6499,
              42.5769
            ],
            [
              -72.6368,
              42.5780
            ]
          ]
        ]
      },
      "properties": {
        "bound": {
          "minx": -72.84832960492308,
          "miny": 42.551093798078455,
          "maxx": -72.63294199986099,
          "maxy": 42.645363000046125
        },
        "Geoid10": 25011042304.000000
      }
    },
    {
      "type": "Feature",
      "id": "523",
      "geometry": {
        "type": "Polygon",
        "coordinates": [
          [
            [
              -72.6755,
              42.5530
            ],
            [
              -72.6730,
              42.5519
            ],
            [
              -72.6692,
              42.5515
            ],
            [
              -72.6637,
              42.5488
            ],
            [
              -72.6610,
              42.5442
            ],
            [
              -72.6557,
              42.5404
            ],
            [
              -72.6522,
              42.5338
            ],
            [
              -72.6487,
              42.5294
            ],
            [
              -72.6609,
              42.4802
            ],
            [
              -72.6628,
              42.4693
            ],
            [
              -72.6562,
              42.4700
            ],
            [
              -72.6574,
              42.4660
            ],
            [
              -72.6557,
              42.4613
            ],
            [
              -72.6573,
              42.4584
            ],
            [
              -72.7577,
              42.4460
            ],
            [
              -72.7571,
              42.4524
            ],
            [
              -72.7660,
              42.4516
            ],
            [
              -72.7651,
              42.4558
            ],
            [
              -72.7591,
              42.4565
            ],
            [
              -72.7583,
              42.4609
            ],
            [
              -72.7643,
              42.4601
            ],
            [
              -72.7637,
              42.4636
            ],
            [
              -72.7735,
              42.4655
            ],
            [
              -72.7733,
              42.4668
            ],
            [
              -72.8315,
              42.4770
            ],
            [
              -72.8315,
              42.4764
            ],
            [
              -72.8712,
              42.4842
            ],
            [
              -72.8752,
              42.5072
            ],
            [
              -72.8703,
              42.5251
            ],
            [
              -72.8755,
              42.5259
            ],
            [
              -72.8767,
              42.5317
            ],
            [
              -72.8770,
              42.5555
            ],
            [
              -72.7754,
              42.5680
            ],
            [
              -72.7454,
              42.5643
            ],
            [
              -72.7422,
              42.5831
            ],
            [
              -72.7193,
              42.5855
            ],
            [
              -72.7182,
              42.5848
            ],
            [
              -72.7172,
              42.5822
            ],
            [
              -72.7152,
              42.5803
            ],
            [
              -72.7112,
              42.5785
            ],
            [
              -72.7086,
              42.5780
            ],
            [
              -72.7064,
              42.5767
            ],
            [
              -72.7064,
              42.5757
            ],
            [
              -72.7068,
              42.5750
            ],
            [
              -72.7070,
              42.5754
            ],
            [
              -72.7073,
              42.5733
            ],
            [
              -72.7066,
              42.5733
            ],
            [
              -72.7065,
              42.5729
            ],
            [
              -72.7071,
              42.5728
            ],
            [
              -72.7072,
              42.5716
            ],
            [
              -72.7067,
              42.5685
            ],
            [
              -72.7054,
              42.5662
            ],
            [
              -72.7038,
              42.5647
            ],
            [
              -72.7003,
              42.5636
            ],
            [
              -72.6948,
              42.5643
            ],
            [
              -72.6927,
              42.5644
            ],
            [
              -72.6909,
              42.5641
            ],
            [
              -72.6853,
              42.5625
            ],
            [
              -72.6817,
              42.5629
            ],
            [
              -72.6802,
              42.5627
            ],
            [
              -72.6794,
              42.5617
            ],
            [
              -72.6796,
              42.5592
            ],
            [
              -72.6789,
              42.5560
            ],
            [
              -72.6758,
              42.5530
            ],
            [
              -72.6755,
              42.5530
            ]
          ]
        ]
      },
      "properties": {
        "bound": {
          "minx": -72.87484251845162,
          "miny": 42.44462120533999,
          "maxx": -72.6497439623843,
          "maxy": 42.58620018866361
        },
        "Geoid10": 25011042304.000000
      }
    },
    {
      "type": "Feature",
      "id": "524",
      "geometry": {
        "type": "Polygon",
        "coordinates": [
          [
            [
              -72.5310,
              42.4289
            ],
            [
              -72.5813,
              42.4225
            ],
            [
              -72.5856,
              42.4232
            ],
            [
              -72.6224,
              42.4152
            ],
            [
              -72.6290,
              42.4149
            ],
            [
              -72.6290,
              42.4143
            ],
            [
              -72.7043,
              42.4055
            ],
            [
              -72.7010,
              42.4529
            ],
            [
              -72.6573,
              42.4584
            ],
            [
              -72.6557,
              42.4613
            ],
            [
              -72.6574,
              42.4660
            ],
            [
              -72.6562,
              42.4700
            ],
            [
              -72.6324,
              42.4728
            ],
            [
              -72.6315,
              42.4683
            ],
            [
              -72.6237,
              42.4690
            ],
            [
              -72.6238,
              42.4699
            ],
            [
              -72.6111,
              42.4712
            ],
            [
              -72.6092,
              42.4640
            ],
            [
              -72.5855,
              42.4668
            ],
            [
              -72.5819,
              42.4721
            ],
            [
              -72.5758,
              42.4781
            ],
            [
              -72.5732,
              42.4795
            ],
            [
              -72.5712,
              42.4819
            ],
            [
              -72.5707,
              42.4837
            ],
            [
              -72.5708,
              42.4882
            ],
            [
              -72.5692,
              42.4915
            ],
            [
              -72.5679,
              42.4974
            ],
            [
              -72.5653,
              42.4999
            ],
            [
              -72.5618,
              42.5023
            ],
            [
              -72.5568,
              42.5065
            ],
            [
              -72.5209,
              42.5102
            ],
            [
              -72.5243,
              42.4765
            ],
            [
              -72.5347,
              42.4585
            ],
            [
              -72.5343,
              42.4422
            ],
            [
              -72.5310,
              42.4289
            ]
          ]
        ]
      },
      "properties": {
        "bound": {
          "minx": -72.70434499947089,
          "miny": 42.40553599990853,
          "maxx": -72.52092800037227,
          "maxy": 42.51022299971276
        },
        "Geoid10": 25011040256.000000
      }
    },
    {
      "type": "Feature",
      "id": "547",
      "geometry": {
        "type": "Polygon",
        "coordinates": [
          [
            [
              -72.5906,
              42.5962
            ],
            [
              -72.5930,
              42.5934
            ],
            [
              -72.5960,
              42.5873
            ],
            [
              -72.5952,
              42.5862
            ],
            [
              -72.5935,
              42.5853
            ],
            [
              -72.5928,
              42.5843
            ],
            [
              -72.5933,
              42.5844
            ],
            [
              -72.5935,
              42.5838
            ],
            [
              -72.5943,
              42.5775
            ],
            [
              -72.5950,
              42.5773
            ],
            [
              -72.5971,
              42.5808
            ],
            [
              -72.5981,
              42.5807
            ],
            [
              -72.6008,
              42.5850
            ],
            [
              -72.6017,
              42.5852
            ],
            [
              -72.6034,
              42.5849
            ],
            [
              -72.6054,
              42.5832
            ],
            [
              -72.6071,
              42.5823
            ],
            [
              -72.6093,
              42.5825
            ],
            [
              -72.6110,
              42.5831
            ],
            [
              -72.6127,
              42.5855
            ],
            [
              -72.6115,
              42.5860
            ],
            [
              -72.6112,
              42.5965
            ],
            [
              -72.6045,
              42.5970
            ],
            [
              -72.6045,
              42.5982
            ],
            [
              -72.5951,
              42.5972
            ],
            [
              -72.5906,
              42.5962
            ]
          ]
        ]
      },
      "properties": {
        "bound": {
          "minx": -72.61259044830334,
          "miny": 42.57711541431581,
          "maxx": -72.59063372746374,
          "maxy": 42.59833006056629
        },
        "Geoid10": 25011042304.000000
      }
    },
    {
      "type": "Feature",
      "id": "548",
      "geometry": {
        "type": "Polygon",
        "coordinates": [
          [
            [
              -72.5906,
              42.5962
            ],
            [
              -72.5951,
              42.5972
            ],
            [
              -72.6045,
              42.5982
            ],
            [
              -72.6045,
              42.5970
            ],
            [
              -72.6112,
              42.5965
            ],
            [
              -72.6110,
              42.6007
            ],
            [
              -72.6113,
              42.6041
            ],
            [
              -72.6118,
              42.6061
            ],
            [
              -72.6090,
              42.6059
            ],
            [
              -72.6061,
              42.6065
            ],
            [
              -72.6020,
              42.6063
            ],
            [
              -72.5984,
              42.6066
            ],
            [
              -72.5910,
              42.6065
            ],
            [
              -72.5853,
              42.6055
            ],
            [
              -72.5810,
              42.6039
            ],
            [
              -72.5842,
              42.6019
            ],
            [
              -72.5906,
              42.5962
            ]
          ]
        ]
      },
      "properties": {
        "bound": {
          "minx": -72.61165615334114,
          "miny": 42.59600712843826,
          "maxx": -72.58101855336248,
          "maxy": 42.6067882922577
        },
        "Geoid10": 25011040256.000000
      }
    },
    {
      "type": "Feature",
      "id": "549",
      "geometry": {
        "type": "Polygon",
        "coordinates": [
          [
            [
              -72.5527,
              42.6122
            ],
            [
              -72.5548,
              42.6122
            ],
            [
              -72.5580,
              42.6113
            ],
            [
              -72.5643,
              42.6078
            ],
            [
              -72.5696,
              42.6041
            ],
            [
              -72.5767,
              42.5968
            ],
            [
              -72.5792,
              42.5955
            ],
            [
              -72.5809,
              42.5952
            ],
            [
              -72.5822,
              42.5944
            ],
            [
              -72.5832,
              42.5924
            ],
            [
              -72.5832,
              42.5903
            ],
            [
              -72.5802,
              42.5868
            ],
            [
              -72.5798,
              42.5847
            ],
            [
              -72.5800,
              42.5816
            ],
            [
              -72.5780,
              42.5779
            ],
            [
              -72.5778,
              42.5751
            ],
            [
              -72.5781,
              42.5737
            ],
            [
              -72.5790,
              42.5716
            ],
            [
              -72.5802,
              42.5709
            ],
            [
              -72.5915,
              42.5698
            ],
            [
              -72.5922,
              42.5718
            ],
            [
              -72.5933,
              42.5722
            ],
            [
              -72.5956,
              42.5751
            ],
            [
              -72.5981,
              42.5807
            ],
            [
              -72.5971,
              42.5808
            ],
            [
              -72.5950,
              42.5773
            ],
            [
              -72.5943,
              42.5775
            ],
            [
              -72.5935,
              42.5838
            ],
            [
              -72.5933,
              42.5844
            ],
            [
              -72.5928,
              42.5843
            ],
            [
              -72.5935,
              42.5853
            ],
            [
              -72.5952,
              42.5862
            ],
            [
              -72.5960,
              42.5873
            ],
            [
              -72.5930,
              42.5934
            ],
            [
              -72.5916,
              42.5953
            ],
            [
              -72.5849,
              42.6013
            ],
            [
              -72.5810,
              42.6039
            ],
            [
              -72.5853,
              42.6055
            ],
            [
              -72.5906,
              42.6065
            ],
            [
              -72.5984,
              42.6066
            ],
            [
              -72.6020,
              42.6063
            ],
            [
              -72.6061,
              42.6065
            ],
            [
              -72.6090,
              42.6059
            ],
            [
              -72.6118,
              42.6061
            ],
            [
              -72.6120,
              42.6067
            ],
            [
              -72.6093,
              42.6088
            ],
            [
              -72.6067,
              42.6101
            ],
            [
              -72.6069,
              42.6105
            ],
            [
              -72.5972,
              42.6152
            ],
            [
              -72.5930,
              42.6183
            ],
            [
              -72.5906,
              42.6206
            ],
            [
              -72.5835,
              42.6286
            ],
            [
              -72.5825,
              42.6287
            ],
            [
              -72.5803,
              42.6317
            ],
            [
              -72.5774,
              42.6347
            ],
            [
              -72.5633,
              42.6473
            ],
            [
              -72.5533,
              42.6548
            ],
            [
              -72.5436,
              42.6559
            ],
            [
              -72.5441,
              42.6553
            ],
            [
              -72.5406,
              42.6557
            ],
            [
              -72.5411,
              42.6520
            ],
            [
              -72.5399,
              42.6508
            ],
            [
              -72.5413,
              42.6485
            ],
            [
              -72.5403,
              42.6459
            ],
            [
              -72.5404,
              42.6451
            ],
            [
              -72.5407,
              42.6448
            ],
            [
              -72.5416,
              42.6449
            ],
            [
              -72.5422,
              42.6453
            ],
            [
              -72.5440,
              42.6443
            ],
            [
              -72.5461,
              42.6443
            ],
            [
              -72.5478,
              42.6420
            ],
            [
              -72.5490,
              42.6412
            ],
            [
              -72.5488,
              42.6373
            ],
            [
              -72.5482,
              42.6363
            ],
            [
              -72.5467,
              42.6352
            ],
            [
              -72.5483,
              42.6326
            ],
            [
              -72.5497,
              42.6320
            ],
            [
              -72.5501,
              42.6312
            ],
            [
              -72.5512,
              42.6303
            ],
            [
              -72.5506,
              42.6288
            ],
            [
              -72.5517,
              42.6270
            ],
            [
              -72.5509,
              42.6264
            ],
            [
              -72.5493,
              42.6265
            ],
            [
              -72.5488,
              42.6258
            ],
            [
              -72.5502,
              42.6243
            ],
            [
              -72.5497,
              42.6225
            ],
            [
              -72.5499,
              42.6207
            ],
            [
              -72.5492,
              42.6199
            ],
            [
              -72.5497,
              42.6181
            ],
            [
              -72.5493,
              42.6175
            ],
            [
              -72.5522,
              42.6151
            ],
            [
              -72.5528,
              42.6133
            ],
            [
              -72.5527,
              42.6122
            ]
          ]
        ]
      },
      "properties": {
        "bound": {
          "minx": -72.61133187242451,
          "miny": 42.56962285561381,
          "maxx": -72.53998073815293,
          "maxy": 42.65589307256282
        },
        "Geoid10": 25011040256.000000
      }
    },
    {
      "type": "Feature",
      "id": "550",
      "geometry": {
        "type": "Polygon",
        "coordinates": [
          [
            [
              -72.6120,
              42.6067
            ],
            [
              -72.6136,
              42.6047
            ],
            [
              -72.6156,
              42.6012
            ],
            [
              -72.6216,
              42.5840
            ],
            [
              -72.6217,
              42.5821
            ],
            [
              -72.6204,
              42.5765
            ],
            [
              -72.6202,
              42.5703
            ],
            [
              -72.6225,
              42.5710
            ],
            [
              -72.6228,
              42.5706
            ],
            [
              -72.6240,
              42.5706
            ],
            [
              -72.6298,
              42.5787
            ],
            [
              -72.6499,
              42.5769
            ],
            [
              -72.6329,
              42.6454
            ],
            [
              -72.5533,
              42.6548
            ],
            [
              -72.5633,
              42.6473
            ],
            [
              -72.5774,
              42.6347
            ],
            [
              -72.5803,
              42.6317
            ],
            [
              -72.5825,
              42.6287
            ],
            [
              -72.5835,
              42.6286
            ],
            [
              -72.5906,
              42.6206
            ],
            [
              -72.5930,
              42.6183
            ],
            [
              -72.5972,
              42.6152
            ],
            [
              -72.6069,
              42.6105
            ],
            [
              -72.6067,
              42.6101
            ],
            [
              -72.6093,
              42.6088
            ],
            [
              -72.6120,
              42.6067
            ]
          ]
        ]
      },
      "properties": {
        "bound": {
          "minx": -72.64980393395535,
          "miny": 42.5700175717899,
          "maxx": -72.55331800044438,
          "maxy": 42.6547690000296
        },
        "Geoid10": 25011040256.000000
      }
    },
    {
      "type": "Feature",
      "id": "553",
      "geometry": {
        "type": "Polygon",
        "coordinates": [
          [
            [
              -72.5568,
              42.5065
            ],
            [
              -72.5618,
              42.5023
            ],
            [
              -72.5653,
              42.4999
            ],
            [
              -72.5679,
              42.4974
            ],
            [
              -72.5692,
              42.4915
            ],
            [
              -72.5708,
              42.4882
            ],
            [
              -72.5707,
              42.4837
            ],
            [
              -72.5712,
              42.4819
            ],
            [
              -72.5732,
              42.4795
            ],
            [
              -72.5758,
              42.4781
            ],
            [
              -72.5819,
              42.4721
            ],
            [
              -72.5855,
              42.4668
            ],
            [
              -72.6092,
              42.4640
            ],
            [
              -72.6111,
              42.4712
            ],
            [
              -72.6238,
              42.4699
            ],
            [
              -72.6237,
              42.4690
            ],
            [
              -72.6315,
              42.4683
            ],
            [
              -72.6324,
              42.4728
            ],
            [
              -72.6628,
              42.4693
            ],
            [
              -72.6609,
              42.4802
            ],
            [
              -72.6487,
              42.5294
            ],
            [
              -72.6522,
              42.5338
            ],
            [
              -72.6557,
              42.5404
            ],
            [
              -72.6610,
              42.5442
            ],
            [
              -72.6637,
              42.5488
            ],
            [
              -72.6692,
              42.5515
            ],
            [
              -72.6730,
              42.5519
            ],
            [
              -72.6755,
              42.5530
            ],
            [
              -72.6553,
              42.5552
            ],
            [
              -72.6520,
              42.5686
            ],
            [
              -72.6389,
              42.5700
            ],
            [
              -72.6368,
              42.5780
            ],
            [
              -72.6298,
              42.5787
            ],
            [
              -72.6239,
              42.5705
            ],
            [
              -72.6228,
              42.5706
            ],
            [
              -72.6225,
              42.5710
            ],
            [
              -72.6210,
              42.5704
            ],
            [
              -72.6183,
              42.5698
            ],
            [
              -72.6159,
              42.5702
            ],
            [
              -72.6137,
              42.5698
            ],
            [
              -72.6093,
              42.5700
            ],
            [
              -72.6077,
              42.5704
            ],
            [
              -72.6054,
              42.5718
            ],
            [
              -72.6033,
              42.5719
            ],
            [
              -72.6018,
              42.5711
            ],
            [
              -72.6010,
              42.5693
            ],
            [
              -72.6002,
              42.5684
            ],
            [
              -72.5965,
              42.5665
            ],
            [
              -72.5951,
              42.5663
            ],
            [
              -72.5939,
              42.5667
            ],
            [
              -72.5926,
              42.5690
            ],
            [
              -72.5915,
              42.5698
            ],
            [
              -72.5807,
              42.5708
            ],
            [
              -72.5792,
              42.5713
            ],
            [
              -72.5778,
              42.5751
            ],
            [
              -72.5781,
              42.5785
            ],
            [
              -72.5751,
              42.5794
            ],
            [
              -72.5736,
              42.5794
            ],
            [
              -72.5704,
              42.5788
            ],
            [
              -72.5653,
              42.5771
            ],
            [
              -72.5624,
              42.5758
            ],
            [
              -72.5611,
              42.5746
            ],
            [
              -72.5601,
              42.5709
            ],
            [
              -72.5566,
              42.5653
            ],
            [
              -72.5557,
              42.5555
            ],
            [
              -72.5560,
              42.5541
            ],
            [
              -72.5612,
              42.5468
            ],
            [
              -72.5639,
              42.5414
            ],
            [
              -72.5683,
              42.5346
            ],
            [
              -72.5689,
              42.5330
            ],
            [
              -72.5689,
              42.5311
            ],
            [
              -72.5671,
              42.5247
            ],
            [
              -72.5659,
              42.5234
            ],
            [
              -72.5649,
              42.5213
            ],
            [
              -72.5634,
              42.5195
            ],
            [
              -72.5571,
              42.5138
            ],
            [
              -72.5558,
              42.5121
            ],
            [
              -72.5551,
              42.5097
            ],
            [
              -72.5553,
              42.5087
            ],
            [
              -72.5568,
              42.5065
            ]
          ]
        ]
      },
      "properties": {
        "bound": {
          "minx": -72.67378267072039,
          "miny": 42.463335339191026,
          "maxx": -72.55608074996529,
          "maxy": 42.579620387529445
        },
        "Geoid10": 25011040256.000000
      }
    },
    {
      "type": "Feature",
      "id": "554",
      "geometry": {
        "type": "Polygon",
        "coordinates": [
          [
            [
              -72.6746,
              42.7329
            ],
            [
              -72.6720,
              42.7195
            ],
            [
              -72.6696,
              42.7165
            ],
            [
              -72.6702,
              42.7133
            ],
            [
              -72.6721,
              42.7126
            ],
            [
              -72.6726,
              42.7109
            ],
            [
              -72.6735,
              42.7107
            ],
            [
              -72.6745,
              42.7083
            ],
            [
              -72.6706,
              42.7079
            ],
            [
              -72.6707,
              42.7034
            ],
            [
              -72.6656,
              42.6999
            ],
            [
              -72.6652,
              42.6985
            ],
            [
              -72.6636,
              42.6973
            ],
            [
              -72.6636,
              42.6961
            ],
            [
              -72.6622,
              42.6943
            ],
            [
              -72.6627,
              42.6937
            ],
            [
              -72.6624,
              42.6928
            ],
            [
              -72.6602,
              42.6918
            ],
            [
              -72.6571,
              42.6910
            ],
            [
              -72.6551,
              42.6897
            ],
            [
              -72.6549,
              42.6891
            ],
            [
              -72.6561,
              42.6864
            ],
            [
              -72.6553,
              42.6860
            ],
            [
              -72.6523,
              42.6856
            ],
            [
              -72.6519,
              42.6850
            ],
            [
              -72.6525,
              42.6838
            ],
            [
              -72.6542,
              42.6836
            ],
            [
              -72.6550,
              42.6830
            ],
            [
              -72.6553,
              42.6812
            ],
            [
              -72.6528,
              42.6798
            ],
            [
              -72.6522,
              42.6770
            ],
            [
              -72.6517,
              42.6765
            ],
            [
              -72.6497,
              42.6753
            ],
            [
              -72.6465,
              42.6746
            ],
            [
              -72.6429,
              42.6729
            ],
            [
              -72.6409,
              42.6704
            ],
            [
              -72.6367,
              42.6699
            ],
            [
              -72.6351,
              42.6678
            ],
            [
              -72.6334,
              42.6663
            ],
            [
              -72.6334,
              42.6654
            ],
            [
              -72.6311,
              42.6648
            ],
            [
              -72.6313,
              42.6629
            ],
            [
              -72.6329,
              42.6617
            ],
            [
              -72.6330,
              42.6611
            ],
            [
              -72.6307,
              42.6602
            ],
            [
              -72.6273,
              42.6596
            ],
            [
              -72.6255,
              42.6580
            ],
            [
              -72.6245,
              42.6559
            ],
            [
              -72.6256,
              42.6552
            ],
            [
              -72.6260,
              42.6543
            ],
            [
              -72.6247,
              42.6523
            ],
            [
              -72.6245,
              42.6514
            ],
            [
              -72.6233,
              42.6510
            ],
            [
              -72.6222,
              42.6514
            ],
            [
              -72.6216,
              42.6511
            ],
            [
              -72.6209,
              42.6497
            ],
            [
              -72.6199,
              42.6492
            ],
            [
              -72.6197,
              42.6486
            ],
            [
              -72.6207,
              42.6476
            ],
            [
              -72.6206,
              42.6469
            ],
            [
              -72.7350,
              42.6332
            ],
            [
              -72.7361,
              42.6321
            ],
            [
              -72.7363,
              42.6313
            ],
            [
              -72.7370,
              42.6289
            ],
            [
              -72.7369,
              42.6270
            ],
            [
              -72.7413,
              42.6275
            ],
            [
              -72.7434,
              42.6271
            ],
            [
              -72.7449,
              42.6261
            ],
            [
              -72.7467,
              42.6242
            ],
            [
              -72.7469,
              42.6227
            ],
            [
              -72.7455,
              42.6213
            ],
            [
              -72.7453,
              42.6197
            ],
            [
              -72.7484,
              42.6180
            ],
            [
              -72.7501,
              42.6182
            ],
            [
              -72.7522,
              42.6201
            ],
            [
              -72.7541,
              42.6210
            ],
            [
              -72.7592,
              42.6199
            ],
            [
              -72.7643,
              42.6194
            ],
            [
              -72.7728,
              42.6201
            ],
            [
              -72.7784,
              42.6211
            ],
            [
              -72.7835,
              42.6213
            ],
            [
              -72.7889,
              42.6202
            ],
            [
              -72.7979,
              42.6176
            ],
            [
              -72.8031,
              42.6166
            ],
            [
              -72.8085,
              42.6170
            ],
            [
              -72.8150,
              42.6167
            ],
            [
              -72.8170,
              42.6171
            ],
            [
              -72.8207,
              42.6186
            ],
            [
              -72.8225,
              42.6188
            ],
            [
              -72.8317,
              42.6166
            ],
            [
              -72.8485,
              42.5591
            ],
            [
              -72.8770,
              42.5555
            ],
            [
              -72.8769,
              42.5412
            ],
            [
              -72.9754,
              42.5559
            ],
            [
              -72.9510,
              42.6410
            ],
            [
              -72.9528,
              42.6509
            ],
            [
              -72.9541,
              42.6514
            ],
            [
              -72.9556,
              42.6546
            ],
            [
              -72.9557,
              42.6584
            ],
            [
              -72.9545,
              42.6623
            ],
            [
              -72.9546,
              42.6650
            ],
            [
              -72.9551,
              42.6659
            ],
            [
              -72.9570,
              42.6668
            ],
            [
              -72.9609,
              42.6673
            ],
            [
              -72.9623,
              42.6668
            ],
            [
              -72.9633,
              42.6648
            ],
            [
              -72.9640,
              42.6642
            ],
            [
              -72.9662,
              42.6640
            ],
            [
              -72.9683,
              42.6642
            ],
            [
              -72.9702,
              42.6639
            ],
            [
              -72.9724,
              42.6630
            ],
            [
              -72.9746,
              42.6611
            ],
            [
              -72.9757,
              42.6609
            ],
            [
              -72.9769,
              42.6615
            ],
            [
              -72.9811,
              42.6647
            ],
            [
              -72.9849,
              42.6658
            ],
            [
              -72.9886,
              42.6673
            ],
            [
              -72.9944,
              42.6721
            ],
            [
              -72.9957,
              42.6738
            ],
            [
              -72.9949,
              42.6744
            ],
            [
              -72.9901,
              42.6741
            ],
            [
              -72.9886,
              42.6744
            ],
            [
              -72.9886,
              42.6758
            ],
            [
              -72.9898,
              42.6782
            ],
            [
              -72.9894,
              42.6785
            ],
            [
              -72.9849,
              42.6792
            ],
            [
              -72.9762,
              42.6791
            ],
            [
              -72.9756,
              42.6797
            ],
            [
              -72.9755,
              42.6805
            ],
            [
              -72.9770,
              42.6831
            ],
            [
              -72.9776,
              42.6857
            ],
            [
              -72.9760,
              42.6864
            ],
            [
              -72.9747,
              42.6887
            ],
            [
              -72.9713,
              42.6890
            ],
            [
              -72.9652,
              42.6877
            ],
            [
              -72.9632,
              42.6877
            ],
            [
              -72.9609,
              42.6885
            ],
            [
              -72.9584,
              42.6900
            ],
            [
              -72.9546,
              42.6901
            ],
            [
              -72.9520,
              42.6927
            ],
            [
              -72.9515,
              42.6941
            ],
            [
              -72.9516,
              42.6955
            ],
            [
              -72.9538,
              42.6982
            ],
            [
              -72.9538,
              42.6986
            ],
            [
              -72.9498,
              42.7017
            ],
            [
              -72.9488,
              42.7041
            ],
            [
              -72.9497,
              42.7051
            ],
            [
              -72.9979,
              42.7013
            ],
            [
              -73.0237,
              42.7027
            ],
            [
              -73.0229,
              42.7411
            ],
            [
              -72.8091,
              42.7366
            ],
            [
              -72.6746,
              42.7329
            ]
          ]
        ]
      },
      "properties": {
        "bound": {
          "minx": -73.01976300705115,
          "miny": 42.5393584971572,
          "maxx": -72.62137317679863,
          "maxy": 42.745720859571705
        },
        "Geoid10": 25011040256.000000
      }
    },
    {
      "type": "Feature",
      "id": "555",
      "geometry": {
        "type": "Polygon",
        "coordinates": [
          [
            [
              -72.5168,
              42.7285
            ],
            [
              -72.4962,
              42.6785
            ],
            [
              -72.4901,
              42.6800
            ],
            [
              -72.4894,
              42.6740
            ],
            [
              -72.4865,
              42.6733
            ],
            [
              -72.4854,
              42.6757
            ],
            [
              -72.4851,
              42.6775
            ],
            [
              -72.4825,
              42.6781
            ],
            [
              -72.4807,
              42.6771
            ],
            [
              -72.4768,
              42.6724
            ],
            [
              -72.4758,
              42.6707
            ],
            [
              -72.4751,
              42.6708
            ],
            [
              -72.4718,
              42.6701
            ],
            [
              -72.4720,
              42.6689
            ],
            [
              -72.4715,
              42.6644
            ],
            [
              -72.4703,
              42.6626
            ],
            [
              -72.4658,
              42.6577
            ],
            [
              -72.4652,
              42.6562
            ],
            [
              -72.4652,
              42.6543
            ],
            [
              -72.4665,
              42.6525
            ],
            [
              -72.4715,
              42.6483
            ],
            [
              -72.4816,
              42.6425
            ],
            [
              -72.4870,
              42.6383
            ],
            [
              -72.4891,
              42.6358
            ],
            [
              -72.4896,
              42.6346
            ],
            [
              -72.4894,
              42.6336
            ],
            [
              -72.4804,
              42.6193
            ],
            [
              -72.4799,
              42.6160
            ],
            [
              -72.4820,
              42.6114
            ],
            [
              -72.4838,
              42.6098
            ],
            [
              -72.4874,
              42.6085
            ],
            [
              -72.4886,
              42.6078
            ],
            [
              -72.4904,
              42.6046
            ],
            [
              -72.4964,
              42.5980
            ],
            [
              -72.4986,
              42.5969
            ],
            [
              -72.5003,
              42.5968
            ],
            [
              -72.5042,
              42.5996
            ],
            [
              -72.5052,
              42.6012
            ],
            [
              -72.5056,
              42.6030
            ],
            [
              -72.5063,
              42.6037
            ],
            [
              -72.5133,
              42.6044
            ],
            [
              -72.5206,
              42.6045
            ],
            [
              -72.5238,
              42.6039
            ],
            [
              -72.5319,
              42.5993
            ],
            [
              -72.5381,
              42.5970
            ],
            [
              -72.5418,
              42.5964
            ],
            [
              -72.5442,
              42.5972
            ],
            [
              -72.5451,
              42.5980
            ],
            [
              -72.5458,
              42.6048
            ],
            [
              -72.5470,
              42.6061
            ],
            [
              -72.5494,
              42.6075
            ],
            [
              -72.5519,
              42.6098
            ],
            [
              -72.5527,
              42.6109
            ],
            [
              -72.5528,
              42.6133
            ],
            [
              -72.5521,
              42.6152
            ],
            [
              -72.5493,
              42.6175
            ],
            [
              -72.5497,
              42.6181
            ],
            [
              -72.5492,
              42.6199
            ],
            [
              -72.5499,
              42.6207
            ],
            [
              -72.5497,
              42.6225
            ],
            [
              -72.5502,
              42.6243
            ],
            [
              -72.5488,
              42.6258
            ],
            [
              -72.5493,
              42.6265
            ],
            [
              -72.5509,
              42.6264
            ],
            [
              -72.5517,
              42.6270
            ],
            [
              -72.5506,
              42.6288
            ],
            [
              -72.5512,
              42.6303
            ],
            [
              -72.5501,
              42.6312
            ],
            [
              -72.5497,
              42.6320
            ],
            [
              -72.5483,
              42.6326
            ],
            [
              -72.5467,
              42.6352
            ],
            [
              -72.5482,
              42.6363
            ],
            [
              -72.5488,
              42.6373
            ],
            [
              -72.5490,
              42.6412
            ],
            [
              -72.5478,
              42.6420
            ],
            [
              -72.5461,
              42.6443
            ],
            [
              -72.5440,
              42.6443
            ],
            [
              -72.5422,
              42.6453
            ],
            [
              -72.5416,
              42.6449
            ],
            [
              -72.5407,
              42.6448
            ],
            [
              -72.5404,
              42.6451
            ],
            [
              -72.5403,
              42.6459
            ],
            [
              -72.5413,
              42.6485
            ],
            [
              -72.5399,
              42.6508
            ],
            [
              -72.5411,
              42.6520
            ],
            [
              -72.5406,
              42.6557
            ],
            [
              -72.5441,
              42.6553
            ],
            [
              -72.5436,
              42.6559
            ],
            [
              -72.6206,
              42.6469
            ],
            [
              -72.6207,
              42.6476
            ],
            [
              -72.6197,
              42.6486
            ],
            [
              -72.6199,
              42.6492
            ],
            [
              -72.6209,
              42.6497
            ],
            [
              -72.6216,
              42.6511
            ],
            [
              -72.6222,
              42.6514
            ],
            [
              -72.6233,
              42.6510
            ],
            [
              -72.6245,
              42.6514
            ],
            [
              -72.6247,
              42.6523
            ],
            [
              -72.6260,
              42.6543
            ],
            [
              -72.6256,
              42.6552
            ],
            [
              -72.6245,
              42.6559
            ],
            [
              -72.6255,
              42.6580
            ],
            [
              -72.6273,
              42.6596
            ],
            [
              -72.6307,
              42.6602
            ],
            [
              -72.6330,
              42.6611
            ],
            [
              -72.6329,
              42.6617
            ],
            [
              -72.6313,
              42.6629
            ],
            [
              -72.6311,
              42.6648
            ],
            [
              -72.6334,
              42.6654
            ],
            [
              -72.6334,
              42.6663
            ],
            [
              -72.6351,
              42.6678
            ],
            [
              -72.6367,
              42.6699
            ],
            [
              -72.6409,
              42.6704
            ],
            [
              -72.6429,
              42.6729
            ],
            [
              -72.6465,
              42.6746
            ],
            [
              -72.6497,
              42.6753
            ],
            [
              -72.6517,
              42.6765
            ],
            [
              -72.6522,
              42.6770
            ],
            [
              -72.6528,
              42.6798
            ],
            [
              -72.6553,
              42.6812
            ],
            [
              -72.6550,
              42.6830
            ],
            [
              -72.6542,
              42.6836
            ],
            [
              -72.6525,
              42.6838
            ],
            [
              -72.6519,
              42.6850
            ],
            [
              -72.6523,
              42.6856
            ],
            [
              -72.6553,
              42.6860
            ],
            [
              -72.6561,
              42.6864
            ],
            [
              -72.6549,
              42.6891
            ],
            [
              -72.6551,
              42.6897
            ],
            [
              -72.6571,
              42.6910
            ],
            [
              -72.6602,
              42.6918
            ],
            [
              -72.6624,
              42.6928
            ],
            [
              -72.6627,
              42.6937
            ],
            [
              -72.6622,
              42.6943
            ],
            [
              -72.6636,
              42.6961
            ],
            [
              -72.6636,
              42.6973
            ],
            [
              -72.6652,
              42.6985
            ],
            [
              -72.6656,
              42.6999
            ],
            [
              -72.6707,
              42.7034
            ],
            [
              -72.6706,
              42.7079
            ],
            [
              -72.6745,
              42.7083
            ],
            [
              -72.6735,
              42.7107
            ],
            [
              -72.6726,
              42.7109
            ],
            [
              -72.6721,
              42.7126
            ],
            [
              -72.6702,
              42.7133
            ],
            [
              -72.6696,
              42.7165
            ],
            [
              -72.6720,
              42.7195
            ],
            [
              -72.6746,
              42.7329
            ],
            [
              -72.5168,
              42.7285
            ]
          ]
        ]
      },
      "properties": {
        "bound": {
          "minx": -72.67238252921608,
          "miny": 42.595130000964815,
          "maxx": -72.46631264978795,
          "maxy": 42.734815857642594
        },
        "Geoid10": 25011040256.000000
      }
    },
    {
      "type": "Feature",
      "id": "578",
      "geometry": {
        "type": "Polygon",
        "coordinates": [
          [
            [
              -72.7010,
              42.4529
            ],
            [
              -72.7043,
              42.4055
            ],
            [
              -72.6692,
              42.4097
            ],
            [
              -72.6721,
              42.3714
            ],
            [
              -72.7771,
              42.3582
            ],
            [
              -72.7736,
              42.4015
            ],
            [
              -72.8056,
              42.3983
            ],
            [
              -72.8054,
              42.4045
            ],
            [
              -72.8162,
              42.4031
            ],
            [
              -72.8155,
              42.4212
            ],
            [
              -72.8356,
              42.4199
            ],
            [
              -72.8341,
              42.4379
            ],
            [
              -72.8479,
              42.4365
            ],
            [
              -72.8556,
              42.4810
            ],
            [
              -72.8315,
              42.4764
            ],
            [
              -72.8315,
              42.4770
            ],
            [
              -72.7733,
              42.4668
            ],
            [
              -72.7735,
              42.4655
            ],
            [
              -72.7637,
              42.4636
            ],
            [
              -72.7643,
              42.4601
            ],
            [
              -72.7583,
              42.4609
            ],
            [
              -72.7591,
              42.4565
            ],
            [
              -72.7651,
              42.4558
            ],
            [
              -72.7660,
              42.4516
            ],
            [
              -72.7571,
              42.4524
            ],
            [
              -72.7577,
              42.4460
            ],
            [
              -72.7010,
              42.4529
            ]
          ]
        ]
      },
      "properties": {
        "bound": {
          "minx": -72.85299503724039,
          "miny": 42.35737656192678,
          "maxx": -72.67055146614297,
          "maxy": 42.48300896182273
        },
        "Geoid10": 25015822336.000000
      }
    },
    {
      "type": "Feature",
      "id": "1007",
      "geometry": {
        "type": "Polygon",
        "coordinates": [
          [
            [
              -72.8769,
              42.5412
            ],
            [
              -72.8767,
              42.5317
            ],
            [
              -72.8755,
              42.5259
            ],
            [
              -72.8703,
              42.5251
            ],
            [
              -72.8752,
              42.5072
            ],
            [
              -72.8712,
              42.4842
            ],
            [
              -72.8556,
              42.4810
            ],
            [
              -72.8479,
              42.4365
            ],
            [
              -72.9046,
              42.4304
            ],
            [
              -72.8858,
              42.3409
            ],
            [
              -72.8852,
              42.3326
            ],
            [
              -72.8948,
              42.3315
            ],
            [
              -72.8956,
              42.3408
            ],
            [
              -72.9538,
              42.3439
            ],
            [
              -73.0001,
              42.3127
            ],
            [
              -73.0016,
              42.3122
            ],
            [
              -73.0020,
              42.3105
            ],
            [
              -73.0035,
              42.3095
            ],
            [
              -73.0037,
              42.3078
            ],
            [
              -73.0058,
              42.3064
            ],
            [
              -73.0058,
              42.3061
            ],
            [
              -73.0052,
              42.3057
            ],
            [
              -73.0054,
              42.3052
            ],
            [
              -73.0068,
              42.3048
            ],
            [
              -73.0079,
              42.3049
            ],
            [
              -73.0092,
              42.3044
            ],
            [
              -73.0105,
              42.3048
            ],
            [
              -73.0113,
              42.3059
            ],
            [
              -73.0130,
              42.3069
            ],
            [
              -73.0146,
              42.3094
            ],
            [
              -73.0168,
              42.3112
            ],
            [
              -73.0178,
              42.3106
            ],
            [
              -73.0183,
              42.3090
            ],
            [
              -73.0196,
              42.3084
            ],
            [
              -73.0207,
              42.3084
            ],
            [
              -73.0220,
              42.3095
            ],
            [
              -73.0246,
              42.3092
            ],
            [
              -73.0267,
              42.3080
            ],
            [
              -73.0296,
              42.3086
            ],
            [
              -73.0317,
              42.3096
            ],
            [
              -73.0356,
              42.3134
            ],
            [
              -73.0388,
              42.3150
            ],
            [
              -73.0398,
              42.3176
            ],
            [
              -73.0397,
              42.3187
            ],
            [
              -73.0407,
              42.3202
            ],
            [
              -73.0420,
              42.3202
            ],
            [
              -73.0448,
              42.3192
            ],
            [
              -73.0458,
              42.3193
            ],
            [
              -73.0467,
              42.3206
            ],
            [
              -73.0498,
              42.3217
            ],
            [
              -73.0522,
              42.3238
            ],
            [
              -73.0629,
              42.3291
            ],
            [
              -73.0644,
              42.3397
            ],
            [
              -73.0686,
              42.3807
            ],
            [
              -73.0659,
              42.3890
            ],
            [
              -73.0117,
              42.3798
            ],
            [
              -73.0032,
              42.4096
            ],
            [
              -72.9882,
              42.4668
            ],
            [
              -72.9865,
              42.4667
            ],
            [
              -72.9794,
              42.4978
            ],
            [
              -72.9686,
              42.5400
            ],
            [
              -72.9791,
              42.5417
            ],
            [
              -72.9754,
              42.5559
            ],
            [
              -72.8769,
              42.5412
            ]
          ]
        ]
      },
      "properties": {
        "bound": {
          "minx": -73.06671032884235,
          "miny": 42.30366914705394,
          "maxx": -72.85048919571724,
          "maxy": 42.55746261376411
        },
        "Geoid10": 25015822336.000000
      }
    }
  ]
}